{"_type":"export","__export_format":4,"__export_date":"2021-05-31T23:41:39.673Z","__export_source":"insomnia.desktop.app:v2021.3.0","resources":[{"_id":"req_fa5f2117ac4d4beba3a8484f3d6ecd78","parentId":"fld_7af9c02787bb492abd6a09c9d2b781ec","modified":1622504201818,"created":1622504155987,"url":"https://mercado-radar-logic-test.herokuapp.com/","name":"Robo Move North","description":"","method":"POST","body":{"mimeType":"application/json","text":"{\n\t\"commands\": \"MMM\"\n}"},"parameters":[],"headers":[{"name":"Content-Type","value":"application/json","id":"pair_5c5541db83434a0581e883d7fafb08f3"}],"authentication":{},"metaSortKey":-1622504155987,"isPrivate":false,"settingStoreCookies":true,"settingSendCookies":true,"settingDisableRenderRequestBody":false,"settingEncodeUrl":true,"settingRebuildPath":true,"settingFollowRedirects":"global","_type":"request"},{"_id":"fld_7af9c02787bb492abd6a09c9d2b781ec","parentId":"wrk_69be7aff2f294424a1e8c6ad6436e481","modified":1622504180013,"created":1622504180013,"name":"Robo Commands","description":"","environment":{},"environmentPropertyOrder":null,"metaSortKey":-1622504180013,"_type":"request_group"},{"_id":"wrk_69be7aff2f294424a1e8c6ad6436e481","parentId":null,"modified":1622504137716,"created":1622504137716,"name":"Commands Robo","description":"","scope":"collection","_type":"workspace"},{"_id":"req_3805ece6f6b04190b429c3e7ac95804d","parentId":"fld_7af9c02787bb492abd6a09c9d2b781ec","modified":1622504281521,"created":1622504248444,"url":"https://mercado-radar-logic-test.herokuapp.com/","name":"Robo Move South","description":"","method":"POST","body":{"mimeType":"application/json","text":"{\n\t\"commands\": \"RRMMM\"\n}"},"parameters":[],"headers":[{"name":"Content-Type","value":"application/json","id":"pair_5c5541db83434a0581e883d7fafb08f3"}],"authentication":{},"metaSortKey":-1622481484977.5,"isPrivate":false,"settingStoreCookies":true,"settingSendCookies":true,"settingDisableRenderRequestBody":false,"settingEncodeUrl":true,"settingRebuildPath":true,"settingFollowRedirects":"global","_type":"request"},{"_id":"req_844276cfa54042b5a22fe8dd29916de8","parentId":"fld_7af9c02787bb492abd6a09c9d2b781ec","modified":1622504308885,"created":1622504259228,"url":"https://mercado-radar-logic-test.herokuapp.com/","name":"Robo Move East","description":"","method":"POST","body":{"mimeType":"application/json","text":"{\n\t\"commands\": \"RMMMM\"\n}"},"parameters":[],"headers":[{"name":"Content-Type","value":"application/json","id":"pair_5c5541db83434a0581e883d7fafb08f3"}],"authentication":{},"metaSortKey":-1622470149472.75,"isPrivate":false,"settingStoreCookies":true,"settingSendCookies":true,"settingDisableRenderRequestBody":false,"settingEncodeUrl":true,"settingRebuildPath":true,"settingFollowRedirects":"global","_type":"request"},{"_id":"req_27c45f3df28649a8a6db086f7c9a8fdb","parentId":"fld_7af9c02787bb492abd6a09c9d2b781ec","modified":1622504299966,"created":1622504266645,"url":"https://mercado-radar-logic-test.herokuapp.com/","name":"Robo Move West","description":"","method":"POST","body":{"mimeType":"application/json","text":"{\n\t\"commands\": \"LMM\"\n}"},"parameters":[],"headers":[{"name":"Content-Type","value":"application/json","id":"pair_5c5541db83434a0581e883d7fafb08f3"}],"authentication":{},"metaSortKey":-1622464481720.375,"isPrivate":false,"settingStoreCookies":true,"settingSendCookies":true,"settingDisableRenderRequestBody":false,"settingEncodeUrl":true,"settingRebuildPath":true,"settingFollowRedirects":"global","_type":"request"},{"_id":"env_84fc0bde0a42fdf7554dafa1f2dd88a58c50fef1","parentId":"wrk_69be7aff2f294424a1e8c6ad6436e481","modified":1622504137996,"created":1622504137996,"name":"Base Environment","data":{},"dataPropertyOrder":null,"color":null,"isPrivate":false,"metaSortKey":1622504137996,"_type":"environment"},{"_id":"jar_84fc0bde0a42fdf7554dafa1f2dd88a58c50fef1","parentId":"wrk_69be7aff2f294424a1e8c6ad6436e481","modified":1622504138040,"created":1622504138040,"name":"Default Jar","cookies":[],"_type":"cookie_jar"},{"_id":"spc_b111443db8884661bce2bc5837e392e6","parentId":"wrk_69be7aff2f294424a1e8c6ad6436e481","modified":1622504137719,"created":1622504137719,"fileName":"Commands Robo","contents":"","contentType":"yaml","_type":"api_spec"}]}